defparse/__init__.py
defparse/parser.py
defparse/typehints.py
defparse-0.1.3.dist-info/LICENSE.md
defparse-0.1.3.dist-info/METADATA
defparse-0.1.3.dist-info/WHEEL
defparse-0.1.3.dist-info/top_level.txt
defparse-0.1.3.dist-info/RECORD
