Metadata-Version: 2.1
Name: defparse
Version: 0.1.3
Summary: Command Line Arguments from Callable Signatures and Docstrings
Home-page: https://github.com/ndoll1998/defparse/tree/master
Author: Niclas Doll
Author-email: niclas@amazonis.net
Classifier: License :: Freely Distributable
Classifier: License :: OSI Approved :: Apache Software License
Classifier: Programming Language :: Python :: 3.9
License-File: LICENSE.md
Requires-Dist: docstring-parser (>=0.15)
